{
	"variants": {
		"orientation=down_east": {
			"model": "industrious:block/leather_roll",
			"x": 90,
			"y": 90
		},
		"orientation=down_north": {
			"model": "industrious:block/leather_roll",
			"x": 90
		},
		"orientation=down_south": {
			"model": "industrious:block/leather_roll",
			"x": 90,
			"y": 180
		},
		"orientation=down_west": {
			"model": "industrious:block/leather_roll",
			"x": 90,
			"y": 270
		},
		"orientation=east_up": {
			"model": "industrious:block/leather_roll",
			"y": 90
		},
		"orientation=north_up": {
			"model": "industrious:block/leather_roll"
		},
		"orientation=south_up": {
			"model": "industrious:block/leather_roll",
			"y": 180
		},
		"orientation=up_east": {
			"model": "industrious:block/leather_roll",
			"x": 270,
			"y": 270
		},
		"orientation=up_north": {
			"model": "industrious:block/leather_roll",
			"x": 270,
			"y": 180
		},
		"orientation=up_south": {
			"model": "industrious:block/leather_roll",
			"x": 270
		},
		"orientation=up_west": {
			"model": "industrious:block/leather_roll",
			"x": 270,
			"y": 90
		},
		"orientation=west_up": {
			"model": "industrious:block/leather_roll",
			"y": 270
		}
	}
}